<?xml version="1.0"?>
<content><metaTitle>Manejo de Cr&#xE9;dito</metaTitle><metaDescription></metaDescription><metaKeywords></metaKeywords><pageTitle>Manejo de Cr&#xE9;dito</pageTitle><shortDesc>Una introducci&#xF3;n sobre temas fundamentales del cr&#xE9;dito.</shortDesc><image></image><imageAlt>../../assets/images/processed/croppedImg_23399.jpeg</imageAlt><sameImage>on</sameImage><template>category</template><contentPage><![CDATA[<p>Este centro de aprendizaje ha sido dise&ntilde;ado para usted como un recurso educativo.</p>
]]></contentPage></content>
